MANIFEST.in
README.md
setup.cfg
setup.py
django_nested_inlines.egg-info/PKG-INFO
django_nested_inlines.egg-info/SOURCES.txt
django_nested_inlines.egg-info/dependency_links.txt
django_nested_inlines.egg-info/top_level.txt
nested_inlines/__init__.py
nested_inlines/admin.py
nested_inlines/forms.py
nested_inlines/helpers.py
nested_inlines/models.py
nested_inlines/views.py