Metadata-Version: 1.1
Name: django-nested-inlines
Version: 0.1
Summary: Adds nested inline support in Django admin
Home-page: https://github.com/phySi0/django-nested-inlines
Author: Alain Trinh
Author-email: i.am@soaa.me
License: MIT License
Download-URL: https://github.com/phySi0/django-nested-inlines/archive/0.1.tar.gz
Platform: UNKNOWN
Classifier: Development Status :: 4 - Beta
Classifier: Environment :: Web Environment
Classifier: Framework :: Django
Classifier: Intended Audience :: Developers
Classifier: License :: OSI Approved :: MIT License
Classifier: Operating System :: OS Independent
Classifier: Programming Language :: Python
Classifier: Topic :: Software Development :: Libraries :: Python Modules
